README.md
setup.py
zdeb_utils/main.py
zdeb_utils.egg-info/PKG-INFO
zdeb_utils.egg-info/SOURCES.txt
zdeb_utils.egg-info/dependency_links.txt
zdeb_utils.egg-info/entry_points.txt
zdeb_utils.egg-info/requires.txt
zdeb_utils.egg-info/top_level.txt