Metadata-Version: 2.1
Name: zdeb-utils
Version: 0.2.0
Summary: Helper to upload and download files to / from Gitlab, as generic packages.
Home-page: UNKNOWN
Author-email: code@zilogic.com
License: UNKNOWN
Platform: UNKNOWN
